znlib/__init__.py
znlib/atomistic/__init__.py
znlib/atomistic/ase.py
znlib/atomistic/cp2k.py
znlib/cli.py
znlib/examples/__init__.py
znlib/examples/general.py
znlib/examples/mc_pi_estimator.py
znlib/scripts/__init__.py
znlib-0.1.1.dist-info/entry_points.txt
znlib-0.1.1.dist-info/LICENSE
znlib-0.1.1.dist-info/WHEEL
znlib-0.1.1.dist-info/METADATA
znlib-0.1.1.dist-info/RECORD
