Metadata-Version: 2.1
Name: znlib
Version: 0.1.1
Summary: 
License: Apache-2.0
Author: zincwarecode
Author-email: zincwarecode@gmail.com
Requires-Python: >=3.8,<4.0.0
Classifier: License :: OSI Approved :: Apache Software License
Classifier: Programming Language :: Python :: 3
Classifier: Programming Language :: Python :: 3.8
Classifier: Programming Language :: Python :: 3.9
Classifier: Programming Language :: Python :: 3.10
Classifier: Programming Language :: Python :: 3.11
Provides-Extra: atomistic
Provides-Extra: zntrack
Requires-Dist: ase (>=3.22.1,<4.0.0); extra == "atomistic"
Requires-Dist: colorama (>=0.4.5,<0.5.0)
Requires-Dist: cp2k-input-tools[yaml] (>=0.8.2,<0.9.0); extra == "atomistic"
Requires-Dist: matplotlib (>=3.6.1,<4.0.0); extra == "zntrack"
Requires-Dist: zntrack (>=0.4.3,<0.5.0); extra == "zntrack" or extra == "atomistic"
Project-URL: repository, https://github.com/zincware/znlib
